Workbook

Sheet Übersicht
A1: Monthly Budget Planner
A2: Feste und variable Kosten, Sparen und Restbudget monatlich planen.
A3: de-DE · EUR · 2026 · soft-pastel
A4: Beschreibung | B4: Wert
A5: Total Income | B5: =SUM('Einnahmen'!$D$5:$D$104) -> 0
A6: Total Expenses | B6: =SUM('Ausgaben'!$D$5:$D$104) -> 0
A7: Remaining Budget | B7: ='Übersicht'!B5-'Übersicht'!B6 -> 0

Sheet Monatsbudget
A1: Monthly Budget Planner
A2: Feste und variable Kosten, Sparen und Restbudget monatlich planen.
A3: de-DE · EUR · 2026 · soft-pastel
A4: Monat | B4: Kategorie | C4: Geplant | D4: Tatsächlich | E4: Verbleibend | F4: Status
A5: JAN | B5: Housing | C5: 1200 | D5: =SUMIFS('Ausgaben'!$D$5:$D$104,'Ausgaben'!$C$5:$C$104,B5,'Ausgaben'!$A$5:$A$104,">="&DATE(2026,MATCH(A5,{"JAN","FEB","MAR","APR","MAY","JUN","JUL","AUG","SEP","OCT","NOV","DEC"},0),1),'Ausgaben'!$A$5:$A$104,"<"&EDATE(DATE(2026,MATCH(A5,{"JAN","FEB","MAR","APR","MAY","JUN","JUL","AUG","SEP","OCT","NOV","DEC"},0),1),1)) -> 0 | E5: =C5-D5 -> 0 | F5: =IF(D5<=C5,"ON_TRACK","OVER_BUDGET") -> 0
A6: JAN | B6: Utilities | C6: 240 | D6: =SUMIFS('Ausgaben'!$D$5:$D$104,'Ausgaben'!$C$5:$C$104,B6,'Ausgaben'!$A$5:$A$104,">="&DATE(2026,MATCH(A6,{"JAN","FEB","MAR","APR","MAY","JUN","JUL","AUG","SEP","OCT","NOV","DEC"},0),1),'Ausgaben'!$A$5:$A$104,"<"&EDATE(DATE(2026,MATCH(A6,{"JAN","FEB","MAR","APR","MAY","JUN","JUL","AUG","SEP","OCT","NOV","DEC"},0),1),1)) -> 0 | E6: =C6-D6 -> 0 | F6: =IF(D6<=C6,"ON_TRACK","OVER_BUDGET") -> 0
A7: JAN | B7: Groceries | C7: 500 | D7: =SUMIFS('Ausgaben'!$D$5:$D$104,'Ausgaben'!$C$5:$C$104,B7,'Ausgaben'!$A$5:$A$104,">="&DATE(2026,MATCH(A7,{"JAN","FEB","MAR","APR","MAY","JUN","JUL","AUG","SEP","OCT","NOV","DEC"},0),1),'Ausgaben'!$A$5:$A$104,"<"&EDATE(DATE(2026,MATCH(A7,{"JAN","FEB","MAR","APR","MAY","JUN","JUL","AUG","SEP","OCT","NOV","DEC"},0),1),1)) -> 0 | E7: =C7-D7 -> 0 | F7: =IF(D7<=C7,"ON_TRACK","OVER_BUDGET") -> 0
A8: JAN | B8: Transport | C8: 250 | D8: =SUMIFS('Ausgaben'!$D$5:$D$104,'Ausgaben'!$C$5:$C$104,B8,'Ausgaben'!$A$5:$A$104,">="&DATE(2026,MATCH(A8,{"JAN","FEB","MAR","APR","MAY","JUN","JUL","AUG","SEP","OCT","NOV","DEC"},0),1),'Ausgaben'!$A$5:$A$104,"<"&EDATE(DATE(2026,MATCH(A8,{"JAN","FEB","MAR","APR","MAY","JUN","JUL","AUG","SEP","OCT","NOV","DEC"},0),1),1)) -> 0 | E8: =C8-D8 -> 0 | F8: =IF(D8<=C8,"ON_TRACK","OVER_BUDGET") -> 0
A9: JAN | B9: Emergency Savings | C9: 300 | D9: =SUMIFS('Ausgaben'!$D$5:$D$104,'Ausgaben'!$C$5:$C$104,B9,'Ausgaben'!$A$5:$A$104,">="&DATE(2026,MATCH(A9,{"JAN","FEB","MAR","APR","MAY","JUN","JUL","AUG","SEP","OCT","NOV","DEC"},0),1),'Ausgaben'!$A$5:$A$104,"<"&EDATE(DATE(2026,MATCH(A9,{"JAN","FEB","MAR","APR","MAY","JUN","JUL","AUG","SEP","OCT","NOV","DEC"},0),1),1)) -> 0 | E9: =C9-D9 -> 0 | F9: =IF(D9<=C9,"ON_TRACK","OVER_BUDGET") -> 0
D10: =SUMIFS('Ausgaben'!$D$5:$D$104,'Ausgaben'!$C$5:$C$104,B10,'Ausgaben'!$A$5:$A$104,">="&DATE(2026,MATCH(A10,{"JAN","FEB","MAR","APR","MAY","JUN","JUL","AUG","SEP","OCT","NOV","DEC"},0),1),'Ausgaben'!$A$5:$A$104,"<"&EDATE(DATE(2026,MATCH(A10,{"JAN","FEB","MAR","APR","MAY","JUN","JUL","AUG","SEP","OCT","NOV","DEC"},0),1),1)) -> 0 | E10: =C10-D10 -> 0 | F10: =IF(D10<=C10,"ON_TRACK","OVER_BUDGET") -> 0
D11: =SUMIFS('Ausgaben'!$D$5:$D$104,'Ausgaben'!$C$5:$C$104,B11,'Ausgaben'!$A$5:$A$104,">="&DATE(2026,MATCH(A11,{"JAN","FEB","MAR","APR","MAY","JUN","JUL","AUG","SEP","OCT","NOV","DEC"},0),1),'Ausgaben'!$A$5:$A$104,"<"&EDATE(DATE(2026,MATCH(A11,{"JAN","FEB","MAR","APR","MAY","JUN","JUL","AUG","SEP","OCT","NOV","DEC"},0),1),1)) -> 0 | E11: =C11-D11 -> 0 | F11: =IF(D11<=C11,"ON_TRACK","OVER_BUDGET") -> 0
D12: =SUMIFS('Ausgaben'!$D$5:$D$104,'Ausgaben'!$C$5:$C$104,B12,'Ausgaben'!$A$5:$A$104,">="&DATE(2026,MATCH(A12,{"JAN","FEB","MAR","APR","MAY","JUN","JUL","AUG","SEP","OCT","NOV","DEC"},0),1),'Ausgaben'!$A$5:$A$104,"<"&EDATE(DATE(2026,MATCH(A12,{"JAN","FEB","MAR","APR","MAY","JUN","JUL","AUG","SEP","OCT","NOV","DEC"},0),1),1)) -> 0 | E12: =C12-D12 -> 0 | F12: =IF(D12<=C12,"ON_TRACK","OVER_BUDGET") -> 0
D13: =SUMIFS('Ausgaben'!$D$5:$D$104,'Ausgaben'!$C$5:$C$104,B13,'Ausgaben'!$A$5:$A$104,">="&DATE(2026,MATCH(A13,{"JAN","FEB","MAR","APR","MAY","JUN","JUL","AUG","SEP","OCT","NOV","DEC"},0),1),'Ausgaben'!$A$5:$A$104,"<"&EDATE(DATE(2026,MATCH(A13,{"JAN","FEB","MAR","APR","MAY","JUN","JUL","AUG","SEP","OCT","NOV","DEC"},0),1),1)) -> 0 | E13: =C13-D13 -> 0 | F13: =IF(D13<=C13,"ON_TRACK","OVER_BUDGET") -> 0
D14: =SUMIFS('Ausgaben'!$D$5:$D$104,'Ausgaben'!$C$5:$C$104,B14,'Ausgaben'!$A$5:$A$104,">="&DATE(2026,MATCH(A14,{"JAN","FEB","MAR","APR","MAY","JUN","JUL","AUG","SEP","OCT","NOV","DEC"},0),1),'Ausgaben'!$A$5:$A$104,"<"&EDATE(DATE(2026,MATCH(A14,{"JAN","FEB","MAR","APR","MAY","JUN","JUL","AUG","SEP","OCT","NOV","DEC"},0),1),1)) -> 0 | E14: =C14-D14 -> 0 | F14: =IF(D14<=C14,"ON_TRACK","OVER_BUDGET") -> 0
D15: =SUMIFS('Ausgaben'!$D$5:$D$104,'Ausgaben'!$C$5:$C$104,B15,'Ausgaben'!$A$5:$A$104,">="&DATE(2026,MATCH(A15,{"JAN","FEB","MAR","APR","MAY","JUN","JUL","AUG","SEP","OCT","NOV","DEC"},0),1),'Ausgaben'!$A$5:$A$104,"<"&EDATE(DATE(2026,MATCH(A15,{"JAN","FEB","MAR","APR","MAY","JUN","JUL","AUG","SEP","OCT","NOV","DEC"},0),1),1)) -> 0 | E15: =C15-D15 -> 0 | F15: =IF(D15<=C15,"ON_TRACK","OVER_BUDGET") -> 0
D16: =SUMIFS('Ausgaben'!$D$5:$D$104,'Ausgaben'!$C$5:$C$104,B16,'Ausgaben'!$A$5:$A$104,">="&DATE(2026,MATCH(A16,{"JAN","FEB","MAR","APR","MAY","JUN","JUL","AUG","SEP","OCT","NOV","DEC"},0),1),'Ausgaben'!$A$5:$A$104,"<"&EDATE(DATE(2026,MATCH(A16,{"JAN","FEB","MAR","APR","MAY","JUN","JUL","AUG","SEP","OCT","NOV","DEC"},0),1),1)) -> 0 | E16: =C16-D16 -> 0 | F16: =IF(D16<=C16,"ON_TRACK","OVER_BUDGET") -> 0
D17: =SUMIFS('Ausgaben'!$D$5:$D$104,'Ausgaben'!$C$5:$C$104,B17,'Ausgaben'!$A$5:$A$104,">="&DATE(2026,MATCH(A17,{"JAN","FEB","MAR","APR","MAY","JUN","JUL","AUG","SEP","OCT","NOV","DEC"},0),1),'Ausgaben'!$A$5:$A$104,"<"&EDATE(DATE(2026,MATCH(A17,{"JAN","FEB","MAR","APR","MAY","JUN","JUL","AUG","SEP","OCT","NOV","DEC"},0),1),1)) -> 0 | E17: =C17-D17 -> 0 | F17: =IF(D17<=C17,"ON_TRACK","OVER_BUDGET") -> 0
D18: =SUMIFS('Ausgaben'!$D$5:$D$104,'Ausgaben'!$C$5:$C$104,B18,'Ausgaben'!$A$5:$A$104,">="&DATE(2026,MATCH(A18,{"JAN","FEB","MAR","APR","MAY","JUN","JUL","AUG","SEP","OCT","NOV","DEC"},0),1),'Ausgaben'!$A$5:$A$104,"<"&EDATE(DATE(2026,MATCH(A18,{"JAN","FEB","MAR","APR","MAY","JUN","JUL","AUG","SEP","OCT","NOV","DEC"},0),1),1)) -> 0 | E18: =C18-D18 -> 0 | F18: =IF(D18<=C18,"ON_TRACK","OVER_BUDGET") -> 0
D19: =SUMIFS('Ausgaben'!$D$5:$D$104,'Ausgaben'!$C$5:$C$104,B19,'Ausgaben'!$A$5:$A$104,">="&DATE(2026,MATCH(A19,{"JAN","FEB","MAR","APR","MAY","JUN","JUL","AUG","SEP","OCT","NOV","DEC"},0),1),'Ausgaben'!$A$5:$A$104,"<"&EDATE(DATE(2026,MATCH(A19,{"JAN","FEB","MAR","APR","MAY","JUN","JUL","AUG","SEP","OCT","NOV","DEC"},0),1),1)) -> 0 | E19: =C19-D19 -> 0 | F19: =IF(D19<=C19,"ON_TRACK","OVER_BUDGET") -> 0
D20: =SUMIFS('Ausgaben'!$D$5:$D$104,'Ausgaben'!$C$5:$C$104,B20,'Ausgaben'!$A$5:$A$104,">="&DATE(2026,MATCH(A20,{"JAN","FEB","MAR","APR","MAY","JUN","JUL","AUG","SEP","OCT","NOV","DEC"},0),1),'Ausgaben'!$A$5:$A$104,"<"&EDATE(DATE(2026,MATCH(A20,{"JAN","FEB","MAR","APR","MAY","JUN","JUL","AUG","SEP","OCT","NOV","DEC"},0),1),1)) -> 0 | E20: =C20-D20 -> 0 | F20: =IF(D20<=C20,"ON_TRACK","OVER_BUDGET") -> 0
D21: =SUMIFS('Ausgaben'!$D$5:$D$104,'Ausgaben'!$C$5:$C$104,B21,'Ausgaben'!$A$5:$A$104,">="&DATE(2026,MATCH(A21,{"JAN","FEB","MAR","APR","MAY","JUN","JUL","AUG","SEP","OCT","NOV","DEC"},0),1),'Ausgaben'!$A$5:$A$104,"<"&EDATE(DATE(2026,MATCH(A21,{"JAN","FEB","MAR","APR","MAY","JUN","JUL","AUG","SEP","OCT","NOV","DEC"},0),1),1)) -> 0 | E21: =C21-D21 -> 0 | F21: =IF(D21<=C21,"ON_TRACK","OVER_BUDGET") -> 0
... D104: =SUMIFS('Ausgaben'!$D$5:$D$104,'Ausgaben'!$C$5:$C$104,B104,'Ausgaben'!$A$5:$A$104,">="&DATE(2026,MATCH(A104,{"JAN","FEB","MAR","APR","MAY","JUN","JUL","AUG","SEP","OCT","NOV","DEC"},0),1),'Ausgaben'!$A$5:$A$104,"<"&EDATE(DATE(2026,MATCH(A104,{"JAN","FEB","MAR","APR","MAY","JUN","JUL","AUG","SEP","OCT","NOV","DEC"},0),1),1)) -> 0 | E104: =C104-D104 -> 0 | F104: =IF(D104<=C104,"ON_TRACK","OVER_BUDGET") -> 0

Sheet Einnahmen
A1: Monthly Budget Planner
A2: Feste und variable Kosten, Sparen und Restbudget monatlich planen.
A3: de-DE · EUR · 2026 · soft-pastel
A4: Datum | B4: Beschreibung | C4: Kategorie | D4: Betrag
A5: 46047.5 | B5: Monthly salary | C5: Salary | D5: 3200
A6: 46053.5 | B6: Freelance project | C6: Freelance Income | D6: 450
A7: 46078.5 | B7: Monthly salary | C7: Salary | D7: 3200

Sheet Ausgaben
A1: Monthly Budget Planner
A2: Feste und variable Kosten, Sparen und Restbudget monatlich planen.
A3: de-DE · EUR · 2026 · soft-pastel
A4: Datum | B4: Beschreibung | C4: Kategorie | D4: Betrag
A5: 46024.5 | B5: Housing payment | C5: Housing | D5: 1200
A6: 46030.5 | B6: Energy and water | C6: Utilities | D6: 218.4
A7: 46036.5 | B7: Household groceries | C7: Groceries | D7: 478.35
A8: 46040.5 | B8: Public transport | C8: Transport | D8: 224.5
A9: 46050.5 | B9: Emergency fund transfer | C9: Emergency Savings | D9: 300

Sheet Kategorien
A1: Monthly Budget Planner
A2: Feste und variable Kosten, Sparen und Restbudget monatlich planen.
A3: de-DE · EUR · 2026 · soft-pastel
A4: Kategorie | B4: Typ | C4: Geplant
A5: Salary | B5: INCOME | C5: 3200
A6: Freelance Income | B6: INCOME | C6: 600
A7: Housing | B7: EXPENSE | C7: 1200
A8: Utilities | B8: EXPENSE | C8: 240
A9: Groceries | B9: EXPENSE | C9: 500
A10: Transport | B10: EXPENSE | C10: 250
A11: Insurance | B11: EXPENSE | C11: 190
A12: Healthcare | B12: EXPENSE | C12: 120
A13: Entertainment | B13: EXPENSE | C13: 180
A14: Emergency Savings | B14: SAVINGS | C14: 300
A15: Long-term Savings | B15: SAVINGS | C15: 250
A16: 100

Sheet Anleitung
A1: Monthly Budget Planner
A2: Feste und variable Kosten, Sparen und Restbudget monatlich planen.
A3: de-DE · EUR · 2026 · soft-pastel
A4: Schritt | B4: Name | C4: Beschreibung
